{
  "Asgarnian ale": 1905,
  "Asgarnian ale (flatpack)": 8520,
  "Bandana eyepatch (blue)": 8926,
  "Bandana eyepatch (brown)": 8927,
  "Bandana eyepatch (red)": 8925,
  "Bandana eyepatch (white)": 8924,
  "Blamish blue shell (pointed)": 3361,
  "Blamish blue shell (round)": 3351,
  "Blamish myre shell (pointed)": 3355,
  "Blamish myre shell (round)": 3345,
  "Blamish ochre shell (pointed)": 3359,
  "Blamish ochre shell (round)": 3349,
  "Blamish red shell (pointed)": 3357,
  "Blamish red shell (round)": 3347,
  "Blood'n'tar snelm (pointed)": 3339,
  "Blood'n'tar snelm (round)": 3329,
  "Broodoo shield (10) (blue)": 6259,
  "Broodoo shield (10) (green)": 6215,
  "Broodoo shield (10) (orange)": 6237,
  "Broodoo shield (blue)": 6279,
  "Broodoo shield (green)": 6235,
  "Broodoo shield (orange)": 6257,
  "Bruise blue snelm (pointed)": 3343,
  "Bruise blue snelm (round)": 3333,
  "Candle lantern (black)": 4532,
  "Candle lantern (white)": 4529,
  "Chef's delight": 5755,
  "Chef's delight (flatpack)": 8526,
  "Cooked chompy": 2878,
  "Cooked chompy (roasted)": 7228,
  "Desert top": 6384,
  "Desert top (overcoat)": 6388,
  "Dragon bitter": 1911,
  "Dragon bitter (flatpack)": 8524,
  "Elven skirt (white)": 24018,
  "Elven skirt (yellow)": 24012,
  "Elven top": -1,
  "Elven top (white vest)": 24027,
  "Elven top (white)": 24015,
  "Elven top (yellow vest)": 24009,
  "Elven top (yellow)": 24021,
  "Greenman's ale": 1909,
  "Greenman's ale (flatpack)": 8522,
  "Karambwan vessel": 3157,
  "Karambwan vessel (baited)": 3159,
  "Mith grapple": 9419,
  "Mith grapple (unf)": 9418,
  "Myre snelm (pointed)": 3337,
  "Myre snelm (round)": 3327,
  "Ochre snelm (pointed)": 3341,
  "Ochre snelm (round)": 3331,
  "Pirate bandana (blue)": 7130,
  "Pirate bandana (brown)": 7136,
  "Pirate bandana (red)": 7124,
  "Pirate bandana (white)": 7112,
  "Pirate leggings (beige)": 7116,
  "Pirate leggings (blue)": 7132,
  "Pirate leggings (brown)": 7138,
  "Pirate leggings (red)": 7126,
  "Priest gown (bottom)": 428,
  "Priest gown (top)": 426,
  "Shirt (brown)": 5030,
  "Shirt (lilac)": 5034,
  "Shirt (yellow)": 5032,
  "Shorts (blue)": 5046,
  "Shorts (brown)": 5042,
  "Shorts (yellow)": 5044,
  "Skirt (blue)": 5052,
  "Skirt (brown)": 5048,
  "Skirt (lilac)": 5050,
  "Snake hide": 6287,
  "Snake hide (swamp)": 7801,
  "Stripy pirate shirt (beige)": 7110,
  "Stripy pirate shirt (blue)": 7128,
  "Stripy pirate shirt (brown)": 7134,
  "Stripy pirate shirt (red)": 7122,
  "Sweetcorn": 5986,
  "Sweetcorn (bowl)": 7088,
  "Tribal mask (blue)": 6339,
  "Tribal mask (green)": 6335,
  "Tribal mask (orange)": 6337,
  "Tribal top (blue)": 6351,
  "Tribal top (brown)": 6341,
  "Tribal top (pink)": 6371,
  "Tribal top (yellow)": 6361,
  "Trousers (blue)": 5040,
  "Trousers (brown)": 5036,
  "Trousers (lilac)": 5038,
  "Villager armband (blue)": 6359,
  "Villager armband (brown)": 6347,
  "Villager armband (pink)": 6379,
  "Villager armband (yellow)": 6369,
  "Villager hat (blue)": 6355,
  "Villager hat (brown)": 6345,
  "Villager hat (pink)": 6375,
  "Villager hat (yellow)": 6365,
  "Villager robe (blue)": 6353,
  "Villager robe (brown)": 6343,
  "Villager robe (pink)": 6373,
  "Villager robe (yellow)": 6363,
  "Villager sandals (blue)": 6357,
  "Villager sandals (brown)": 6349,
  "Villager sandals (pink)": 6377,
  "Villager sandals (yellow)": 6367,
  "Woven top (blue)": 5026,
  "Woven top (brown)": 5024,
  "Woven top (yellow)": 5028,
  "Yak-hide armour (legs)": 10824,
  "Yak-hide armour (top)": 10822
}